pretix_adyen/__init__.py
pretix_adyen/apps.py
pretix_adyen/payment.py
pretix_adyen/paymentmethods.py
pretix_adyen/signals.py
pretix_adyen/urls.py
pretix_adyen/views.py
pretix_adyen/locale/django.pot
pretix_adyen/locale/cs/LC_MESSAGES/django.mo
pretix_adyen/locale/cs/LC_MESSAGES/django.po
pretix_adyen/locale/de/LC_MESSAGES/django.mo
pretix_adyen/locale/de/LC_MESSAGES/django.po
pretix_adyen/locale/de_Informal/.gitkeep
pretix_adyen/locale/de_Informal/LC_MESSAGES/django.mo
pretix_adyen/locale/de_Informal/LC_MESSAGES/django.po
pretix_adyen/locale/es/LC_MESSAGES/django.mo
pretix_adyen/locale/es/LC_MESSAGES/django.po
pretix_adyen/locale/hr/LC_MESSAGES/django.mo
pretix_adyen/locale/hr/LC_MESSAGES/django.po
pretix_adyen/locale/nl/LC_MESSAGES/django.mo
pretix_adyen/locale/nl/LC_MESSAGES/django.po
pretix_adyen/locale/nl_Informal/LC_MESSAGES/django.mo
pretix_adyen/locale/nl_Informal/LC_MESSAGES/django.po
pretix_adyen/locale/sk/LC_MESSAGES/django.mo
pretix_adyen/locale/sk/LC_MESSAGES/django.po
pretix_adyen/locale/uk/LC_MESSAGES/django.mo
pretix_adyen/locale/uk/LC_MESSAGES/django.po
pretix_adyen/static/pretix_adyen/.gitkeep
pretix_adyen/static/pretix_adyen/adyen_logo.svg
pretix_adyen/static/pretix_adyen/pretix-adyen.css
pretix_adyen/static/pretix_adyen/pretix-adyen.js
pretix_adyen/templates/pretix_adyen/.gitkeep
pretix_adyen/templates/pretix_adyen/checkout_payment_confirm.html
pretix_adyen/templates/pretix_adyen/checkout_payment_form.html
pretix_adyen/templates/pretix_adyen/control.html
pretix_adyen/templates/pretix_adyen/control_settings.html
pretix_adyen/templates/pretix_adyen/pending.html
pretix_adyen/templates/pretix_adyen/presale_head.html
pretix_adyen/templates/pretix_adyen/sca.html
pretix_adyen-1.5.0.dist-info/licenses/LICENSE
pretix_adyen-1.5.0.dist-info/METADATA
pretix_adyen-1.5.0.dist-info/WHEEL
pretix_adyen-1.5.0.dist-info/entry_points.txt
pretix_adyen-1.5.0.dist-info/top_level.txt
pretix_adyen-1.5.0.dist-info/RECORD
