Metadata-Version: 2.4
Name: pretix-adyen
Version: 1.5.0
Summary: This plugin allows to use Adyen as a payment provider
Author-email: pretix team <support@pretix.eu>
Maintainer-email: pretix team <support@pretix.eu>
License: Copyright 2020 Raphael Michel
Project-URL: homepage, https://code.rami.io/pretix/pretix-adyen
Keywords: pretix
Requires-Python: >=3.9
License-File: LICENSE
Requires-Dist: Adyen==13.0.*
Dynamic: license-file
